dvs/VERSION
dvs/__init__.py
dvs/_dvs.py
dvs/config.py
dvs/db/__init__.py
dvs/db/api.py
dvs/db/documents/__init__.py
dvs/db/documents/api.py
dvs/db/manifest/__init__.py
dvs/db/manifest/api.py
dvs/db/points/__init__.py
dvs/db/points/api.py
dvs/tokens/__init__.py
dvs/types/__init__.py
dvs/types/columns.py
dvs/types/document.py
dvs/types/encoding_type.py
dvs/types/health_response.py
dvs/types/manifest.py
dvs/types/paginations.py
dvs/types/point.py
dvs/types/search_request.py
dvs/types/search_result.py
dvs/utils/__init__.py
dvs/utils/chunk.py
dvs/utils/datasets/__init__.py
dvs/utils/datasets/_download.py
dvs/utils/datasets/bbc.py
dvs/utils/display.py
dvs/utils/dummies.py
dvs/utils/ensure.py
dvs/utils/hash.py
dvs/utils/ids.py
dvs/utils/is_.py
dvs/utils/openapi.py
dvs/utils/sql_stmts.py
dvs/utils/timer.py
dvs/utils/to.py
dvs/utils/vss.py
dvs/version.py
dvs_py-1.1.0.dist-info/LICENSE
dvs_py-1.1.0.dist-info/METADATA
dvs_py-1.1.0.dist-info/WHEEL
dvs_py-1.1.0.dist-info/RECORD
