Metadata-Version: 2.3
Name: dvs-py
Version: 1.1.0
Summary: Deploy simple vector similarity search service by DuckDB.
License: MIT
Author: allen2c
Author-email: f1470891079@gmail.com
Requires-Python: >=3.11,<4
Classifier: License :: OSI Approved :: MIT License
Classifier: Programming Language :: Python :: 3
Classifier: Programming Language :: Python :: 3.11
Classifier: Programming Language :: Python :: 3.12
Classifier: Programming Language :: Python :: 3.13
Provides-Extra: all
Requires-Dist: chunkle
Requires-Dist: diskcache
Requires-Dist: duckdb (>=1,<2)
Requires-Dist: logging-bullet-train
Requires-Dist: numpy (>=2,<3)
Requires-Dist: openai (>=1,<2)
Requires-Dist: openai-embeddings-model (>=0.3.0,<1)
Requires-Dist: pydantic (>=2,<3)
Requires-Dist: pydantic-settings
Requires-Dist: str-or-none
Requires-Dist: tiktoken
Requires-Dist: uuid-utils
Project-URL: Homepage, https://github.com/allen2c/dvs
Project-URL: Repository, https://github.com/allen2c/dvs
